reddit_to_sqlite/__init__.py
reddit_to_sqlite/main.py
reddit_to_sqlite/reddit_instance.py
reddit_to_sqlite/view_def.sql
reddit_to_sqlite-0.1.0.dist-info/entry_points.txt
reddit_to_sqlite-0.1.0.dist-info/LICENSE
reddit_to_sqlite-0.1.0.dist-info/WHEEL
reddit_to_sqlite-0.1.0.dist-info/METADATA
reddit_to_sqlite-0.1.0.dist-info/RECORD
