Metadata-Version: 2.1
Name: reddit-to-sqlite
Version: 0.1.0
Summary: 
Author: Catherine Devlin
Author-email: catherine.devlin@gmail.com
Requires-Python: >=3.9,<4.0
Classifier: Programming Language :: Python :: 3
Classifier: Programming Language :: Python :: 3.9
Requires-Dist: praw (>=7.2.0,<8.0.0)
Requires-Dist: sqlite-utils (>=3.6,<4.0)
Requires-Dist: typer[all] (>=0.3.2,<0.4.0)
